translation_sdk/__init__.py
translation_sdk/constants.py
translation_sdk/errors.py
translation_sdk/py.typed
translation_sdk/translation_api_sdk.py
translation_sdk/translation_api_sdk_config.py
translation_sdk/__tests__/__init__.py
translation_sdk/__tests__/test_api_sdk.py
translation_sdk/helpers/__init__.py
translation_sdk/helpers/redis_client.py
translation_sdk/modules/__init__.py
translation_sdk/modules/translation_page.py
translation_sdk/modules/translation_session.py
translation_sdk/templates/__init__.py
translation_sdk/templates/service_translations.html
translation_sdk/types/__init__.py
translation_sdk/types/translation_cache.py
translation_sdk/types/translation_chache_query.py
translation_sdk/utils/__init__.py
translation_sdk/utils/internal_api_error_handler.py
translation_sdk/utils/storage_redis_cache.py
ul_translation_sdk-2.0.8.dist-info/METADATA
ul_translation_sdk-2.0.8.dist-info/WHEEL
ul_translation_sdk-2.0.8.dist-info/top_level.txt
ul_translation_sdk-2.0.8.dist-info/RECORD
